miniseer/__init__.py
miniseer-0.0.1.dist-info/METADATA
miniseer-0.0.1.dist-info/WHEEL
miniseer-0.0.1.dist-info/top_level.txt
miniseer-0.0.1.dist-info/RECORD
