Metadata-Version: 2.1
Name: miniseer
Version: 0.0.1
Summary: ML Automation
Home-page: http://github.com/znrm/miniseer
Author: Zaniar Moradian
Author-email: zaniarmoradian@gmail.com
License: MIT
Platform: UNKNOWN
Classifier: Programming Language :: Python :: 3
Classifier: License :: OSI Approved :: MIT License
Classifier: Operating System :: OS Independent
Classifier: Development Status :: 1 - Planning
